<status_log><miner_status><datetime>2019-04-03 20:15:34.888164</datetime><hashrate>501</hashrate><elapsed_time>2h35m13s</elapsed_time><fan1_rpm>1500</fan1_rpm><pool_status><url>url</url><worker>worker</worker><accepted>12</accepted><rejected>3</rejected><stales>5</stales></pool_status><pool_status><url>url</url><worker>worker</worker><accepted>12</accepted><rejected>3</rejected><stales>5</stales></pool_status><pool_status><url>url</url><worker>worker</worker><accepted>12</accepted><rejected>3</rejected><stales>5</stales></pool_status><hashboard_status><hw_errors>5</hw_errors><temp_pcb>40</temp_pcb><temp_chip>45</temp_chip><chip_status> oooooooo oooooooo </chip_status></hashboard_status><hashboard_status><hw_errors>5</hw_errors><temp_pcb>40</temp_pcb><temp_chip>45</temp_chip><chip_status> oooooooo oooooooo </chip_status></hashboard_status><hashboard_status><hw_errors>5</hw_errors><temp_pcb>40</temp_pcb><temp_chip>45</temp_chip><chip_status> oooooooo oooooooo </chip_status></hashboard_status><hashboard_status><hw_errors>5</hw_errors><temp_pcb>40</temp_pcb><temp_chip>45</temp_chip><chip_status> oooooooo oooooooo </chip_status></hashboard_status><fan2_rpm>1300</fan2_rpm></miner_status><miner_status><datetime>2019-04-03 20:47:26.747491</datetime><hashrate>501</hashrate><elapsed_time>2h35m13s</elapsed_time><fan1_rpm>1500</fan1_rpm><pool_status><url>url</url><worker>worker</worker><accepted>12</accepted><rejected>3</rejected><stales>5</stales></pool_status><pool_status><url>url</url><worker>worker</worker><accepted>12</accepted><rejected>3</rejected><stales>5</stales></pool_status><pool_status><url>url</url><worker>worker</worker><accepted>12</accepted><rejected>3</rejected><stales>5</stales></pool_status><hashboard_status><hw_errors>5</hw_errors><temp_pcb>40</temp_pcb><temp_chip>45</temp_chip><chip_status> oooooooo oooooooo </chip_status></hashboard_status><hashboard_status><hw_errors>5</hw_errors><temp_pcb>40</temp_pcb><temp_chip>45</temp_chip><chip_status> oooooooo oooooooo </chip_status></hashboard_status><hashboard_status><hw_errors>5</hw_errors><temp_pcb>40</temp_pcb><temp_chip>45</temp_chip><chip_status> oooooooo oooooooo </chip_status></hashboard_status><hashboard_status><hw_errors>5</hw_errors><temp_pcb>40</temp_pcb><temp_chip>45</temp_chip><chip_status> oooooooo oooooooo </chip_status></hashboard_status><fan2_rpm>1300</fan2_rpm></miner_status></status_log>